firebase_auth/__init__.py
firebase_auth/apps.py
firebase_auth/authentication.py
firebase_auth/forms.py
firebase_auth/models.py
graphene_django_firebase_auth-0.0.22.dist-info/LICENSE
graphene_django_firebase_auth-0.0.22.dist-info/METADATA
graphene_django_firebase_auth-0.0.22.dist-info/WHEEL
graphene_django_firebase_auth-0.0.22.dist-info/top_level.txt
graphene_django_firebase_auth-0.0.22.dist-info/RECORD
