Metadata-Version: 2.1
Name: graphene-django-firebase-auth
Version: 0.0.22
Summary: Authentication provider for graphene-django and Google Firebase's Authentication service.
Home-page: https://github.com/dspacejs/graphene-django-firebase-auth
Author: Daniel Spajic
Author-email: daniel@danieljs.tech
License: MIT
Keywords: graphene django firebase auth
Classifier: Development Status :: 3 - Alpha
Classifier: Environment :: Web Environment
Classifier: Framework :: Django
Classifier: Framework :: Django :: 2.1
Classifier: Intended Audience :: Developers
Classifier: Operating System :: OS Independent
Classifier: Programming Language :: Python
Classifier: Programming Language :: Python :: 3.7
Classifier: Topic :: Software Development :: Libraries :: Python Modules
Classifier: License :: OSI Approved :: MIT License
License-File: LICENSE
Requires-Dist: django
Requires-Dist: firebase-admin
